openproteindesign/__init__.py
openproteindesign-0.1.dev0.dist-info/LICENSE
openproteindesign-0.1.dev0.dist-info/METADATA
openproteindesign-0.1.dev0.dist-info/WHEEL
openproteindesign-0.1.dev0.dist-info/top_level.txt
openproteindesign-0.1.dev0.dist-info/RECORD
