Metadata-Version: 2.1
Name: openproteindesign
Version: 0.1.dev0
Summary: A general purpose Protein Design Package
Home-page: https://github.com/openproteindesign/openproteindesign
Author: Dominik Lemm
Author-email: lemm92.d@gmail.com
License: UNKNOWN
Platform: UNKNOWN
Classifier: Programming Language :: Python :: 3
Classifier: License :: OSI Approved :: MIT License
Classifier: Operating System :: OS Independent
